Metadata-Version: 2.1
Name: pyinspirehep
Version: 1.1.0
Summary: A simple python wrapper for inspirehep API
Home-page: https://github.com/javadebadi/pyinspirehep
Author: Javad Ebadi, Vahid Hoseinzade
Author-email: javad.ebadi.1990@gmail.com, vahid.hoseinzade64@gmail.com
License: MIT
Platform: UNKNOWN
Requires-Python: >=3.7
